pycno/__init__.py
pycno/data/MWDB_Coasts_Countries_3.cnob
pycno/data/README.md
pycno/data/test.cno
pycno/data/test.cnob
pycno/tests/__init__.py
pycno/tests/test_cno.py
pycno/util/__init__.py
pycno/util/shp2cno.py
pycno-0.3.2.dist-info/LICENSE
pycno-0.3.2.dist-info/METADATA
pycno-0.3.2.dist-info/WHEEL
pycno-0.3.2.dist-info/top_level.txt
pycno-0.3.2.dist-info/RECORD
