Metadata-Version: 2.1
Name: pycno
Version: 0.3.2
Summary: Python map overlay software to read CNO and CNOB files.
Home-page: https://github.com/barronh/pycno
Author: Barron H. Henderson
Author-email: barronh@gmail.com
Classifier: Programming Language :: Python :: 3
Classifier: License :: OSI Approved :: GNU General Public License v3 (GPLv3)
Classifier: Development Status :: 2 - Pre-Alpha
Classifier: Operating System :: OS Independent
Requires-Python: >=3.6
License-File: LICENSE
Requires-Dist: numpy
Requires-Dist: matplotlib
Provides-Extra: proj
Requires-Dist: pyproj ; extra == 'proj'
